docker_shell/Configuration.py
docker_shell/DaemonSelection.py
docker_shell/DockerShell.py
docker_shell/Utility.py
docker_shell/__init__.py
docker_shell/__main__.py
docker_shell/entrypoints.py
docker_shell-0.0.9.dist-info/LICENSE
docker_shell-0.0.9.dist-info/METADATA
docker_shell-0.0.9.dist-info/WHEEL
docker_shell-0.0.9.dist-info/entry_points.txt
docker_shell-0.0.9.dist-info/top_level.txt
docker_shell-0.0.9.dist-info/zip-safe
docker_shell-0.0.9.dist-info/RECORD
