Metadata-Version: 2.1
Name: docker-shell
Version: 0.0.9
Summary: Docker Interactive Shell Runner
Home-page: http://github.com/adamrehn/docker-shell
Author: Adam Rehn
Author-email: adam@adamrehn.com
License: MIT
Keywords: docker interactive console terminal
Platform: UNKNOWN
Classifier: License :: OSI Approved :: MIT License
Classifier: Programming Language :: Python :: 3.5
Classifier: Programming Language :: Python :: 3.6
Classifier: Programming Language :: Python :: 3.7
Classifier: Programming Language :: Python :: 3.8
Classifier: Programming Language :: Python :: 3.9
Classifier: Environment :: Console
Requires-Python: >=3.5
Requires-Dist: docker (>=4.0.0)
Requires-Dist: packaging (>=19.1)
Requires-Dist: setuptools (>=38.6.0)
Requires-Dist: twine (>=1.11.0)
Requires-Dist: wheel (>=0.31.0)
